gpiowrapper/__init__.py
gpiowrapper/base.py
gpiowrapper/util.py
gpiowrapper/raspi/__init__.py
gpiowrapper/raspi/raspi_base.py
gpiowrapper/raspi/rpi_gpio_library.py
gpiowrapperTests/__init__.py
gpiowrapperTests/base_test.py
gpiowrapperTests/useful_test_util.py
gpiowrapperTests/util_test.py
gpiowrapperTests/raspi/__init__.py
gpiowrapperTests/raspi/raspi_base_test.py
gpiowrapperTests/raspi/rpi_gpio_library_test.py
gpiowrapper-0.1.2.dist-info/LICENSE
gpiowrapper-0.1.2.dist-info/METADATA
gpiowrapper-0.1.2.dist-info/WHEEL
gpiowrapper-0.1.2.dist-info/top_level.txt
gpiowrapper-0.1.2.dist-info/RECORD
